src/ALU.sv
module ALU (
    input [2:0] ALU_Oper,
    input [7:0] A, B,
    output [7:0] ALU_Out,
    output CY
);

assign {CY, ALU_Out} = ALU_Oper[2] ? 
                        (ALU_Oper[1] ? 
                            (ALU_Oper[0] ? 
                                ((A > B) ? ({1'b0, 8'b1}) : ({1'b0, 8'b0})) : // If A > B
                                ({1'b0, ~(A & B)})) : // NAND
                            (ALU_Oper[0] ? 
                                ({A[0], A >> 1}) :  // SHR
                                ({A[7], A << 1}))) :  // SHL
                        (ALU_Oper[1] ? 
                            (ALU_Oper[0] ? 
                                ({1'b0, A} - 1) : // Decrement
                                ({1'b0, A} - {1'b0, B})) :  // Subtract
                            (ALU_Oper[0] ? 
                                ({1'b0, A} + 1) : // Increment
                                ({1'b0, A} + {1'b0, B}))); // Add
endmodule

tb/ALU_tb.sv
module ALU_tb;
    reg [2:0] ALU_Oper;
    reg [7:0] A, B;
    wire [7:0] ALU_Out;
    wire CY;
    
    ALU uut (
        .ALU_Oper(ALU_Oper),
        .A(A),
        .B(B),
        .ALU_Out(ALU_Out),
        .CY(CY)
    );
    
    initial begin
      $dumpfile("dump.vcd");
    	$dumpvars(0, ALU_tb);
        // Add: A = 8'hFF, B = 9
        ALU_Oper = 3'b000; A = 8'hFF; B = 8'd9;
       	#10;
      	// Increment: A = 1
        ALU_Oper = 3'b001; A = 8'd1; B = 8'hBB;
      	#10;
        // Subtract: A = 8'h25, B = 3
        ALU_Oper = 3'b010; A = 8'h25; B = 8'd3;
      	#10;
        // Decrement: A = 8'h13
        ALU_Oper = 3'b011; A = 8'h13; B = 8'hBB;
      	#10;
        // Shift Left (SHL): A = 8'hAA, B = 9
        ALU_Oper = 3'b100; A = 8'hAA; B = 8'd9;
      	#10;
        // Shift Right (SHR): A = 8'h55, B = 8'hBB
        ALU_Oper = 3'b101; A = 8'h55; B = 8'hBB;
      	#10;
        // NAND: A = 8'hAA, B = 8'h5A
        ALU_Oper = 3'b110; A = 8'hAA; B = 8'h5A;
      	#10;
      	// If A > B: A = 8'h13, B = 8'h12
        ALU_Oper = 3'b111; A = 8'h13; B = 8'h12;
      	#10;
        $finish;
    end
endmodule

dump.vcd
$date
	Thu Nov  7 22:29:04 2024
$end
$version
	Icarus Verilog
$end
$timescale
	1s
$end
$scope module ALU_tb $end
$var wire 1 ! CY $end
$var wire 8 " ALU_Out [7:0] $end
$var reg 8 # A [7:0] $end
$var reg 3 $ ALU_Oper [2:0] $end
$var reg 8 % B [7:0] $end
$scope module uut $end
$var wire 8 & A [7:0] $end
$var wire 3 ' ALU_Oper [2:0] $end
$var wire 8 ( B [7:0] $end
$var reg 8 ) ALU_Out [7:0] $end
$var reg 1 ! CY $end
$upscope $end
$upscope $end
$enddefinitions $end
$comment Show the parameter values. $end
$dumpall
$end
#0
$dumpvars
b1000 )
b1001 (
b0 '
b11111111 &
b1001 %
b0 $
b11111111 #
b1000 "
0!
$end
#10
b10 "
b10 )
b10111011 %
b10111011 (
b1 #
b1 &
b1 $
b1 '
#20
b100010 "
b100010 )
b11 %
b11 (
b100101 #
b100101 &
b10 $
b10 '
#30
b10010 "
b10010 )
b10111011 %
b10111011 (
b10011 #
b10011 &
b11 $
b11 '
#40
1!
b1010100 "
b1010100 )
b1001 %
b1001 (
b10101010 #
b10101010 &
b100 $
b100 '
#50
b101010 "
b101010 )
b10111011 %
b10111011 (
b1010101 #
b1010101 &
b101 $
b101 '
#60
0!
b11110101 "
b11110101 )
b1011010 %
b1011010 (
b10101010 #
b10101010 &
b110 $
b110 '
#70
b1 "
b1 )
b10010 %
b10010 (
b10011 #
b10011 &
b111 $
b111 '
